understory/apps/tracker/__init__.py
understory/apps/tracker/templates/__init__.py
understory/apps/tracker/templates/physical.html
understory/apps/tracker/templates/trip.html
understory/apps/tracker/templates/web.html
understory_tracker-0.0.3.dist-info/entry_points.txt
understory_tracker-0.0.3.dist-info/LICENSE
understory_tracker-0.0.3.dist-info/WHEEL
understory_tracker-0.0.3.dist-info/METADATA
understory_tracker-0.0.3.dist-info/RECORD
