Metadata-Version: 2.1
Name: understory-tracker
Version: 0.0.3
Summary: Personal tracker for your personal website.
License: CC0-1.0
Author: Angelo Gladding
Author-email: self@angelogladding.com
Requires-Python: >=3.9,<4.0
Classifier: License :: CC0 1.0 Universal (CC0 1.0) Public Domain Dedication
Classifier: Programming Language :: Python :: 3
Classifier: Programming Language :: Python :: 3.9
Requires-Dist: understory (>=0,<1)
